obci_readmanager/__init__.py
obci_readmanager/_version.py
obci_readmanager/debug.py
obci_readmanager/signal_processing/__init__.py
obci_readmanager/signal_processing/logging.py
obci_readmanager/signal_processing/read_manager.py
obci_readmanager/signal_processing/smart_tags_manager.py
obci_readmanager/signal_processing/types_utils.py
obci_readmanager/signal_processing/balance/__init__.py
obci_readmanager/signal_processing/balance/raw_analysis.py
obci_readmanager/signal_processing/balance/raw_preprocessing.py
obci_readmanager/signal_processing/balance/wii_analysis.py
obci_readmanager/signal_processing/balance/wii_preprocessing.py
obci_readmanager/signal_processing/balance/wii_read_manager.py
obci_readmanager/signal_processing/balance/wii_utils.py
obci_readmanager/signal_processing/buffers/__init__.py
obci_readmanager/signal_processing/buffers/auto_blink_buffer.py
obci_readmanager/signal_processing/buffers/auto_ring_buffer.py
obci_readmanager/signal_processing/buffers/ring_buffer.py
obci_readmanager/signal_processing/buffers/ring_buffer_base.py
obci_readmanager/signal_processing/mne_utils/__init__.py
obci_readmanager/signal_processing/mne_utils/read_manager_mne_mixin.py
obci_readmanager/signal_processing/mne_utils/smart_tags_mne_mixin.py
obci_readmanager/signal_processing/mne_utils/utils.py
obci_readmanager/signal_processing/signal/__init__.py
obci_readmanager/signal_processing/signal/data_ascii_write_proxy.py
obci_readmanager/signal_processing/signal/data_buffered_write_proxy.py
obci_readmanager/signal_processing/signal/data_generic_write_proxy.py
obci_readmanager/signal_processing/signal/data_raw_write_proxy.py
obci_readmanager/signal_processing/signal/data_read_proxy.py
obci_readmanager/signal_processing/signal/data_write_proxy.py
obci_readmanager/signal_processing/signal/generic_info_file_proxy.py
obci_readmanager/signal_processing/signal/info_file_proxy.py
obci_readmanager/signal_processing/signal/read_data_source.py
obci_readmanager-1.1.3.dist-info/DESCRIPTION.rst
obci_readmanager-1.1.3.dist-info/METADATA
obci_readmanager-1.1.3.dist-info/RECORD
obci_readmanager-1.1.3.dist-info/WHEEL
obci_readmanager-1.1.3.dist-info/metadata.json
obci_readmanager-1.1.3.dist-info/top_level.txt
