Metadata-Version: 2.0
Name: obci-readmanager
Version: 1.1.3
Summary: OpenBCI 2 readmanager support module
Home-page: UNKNOWN
Author: BrainTech
Author-email: admin@braintech.pl
License: GNU General Public License v3 or later (GPLv3+)
Keywords: bci eeg openbci
Platform: UNKNOWN
Classifier: Development Status :: 3 - Alpha
Classifier: Natural Language :: English
Classifier: Topic :: Scientific/Engineering
Classifier: Intended Audience :: Developers
Classifier: License :: OSI Approved :: GNU General Public License v3 or later (GPLv3+)
Classifier: Programming Language :: Python :: 3
Classifier: Programming Language :: Python :: 3.5
Classifier: Operating System :: POSIX :: Linux
Classifier: Environment :: Console
Requires-Dist: mne (~=0.17.0)
Provides-Extra: test
Requires-Dist: pytest-runner (>=2.9); extra == 'test'
Requires-Dist: pytest (>=3.0); extra == 'test'
Requires-Dist: pytest-cov (>=2.3.1); extra == 'test'
Requires-Dist: pytest-timeout (>=1.0); extra == 'test'
Requires-Dist: pytest-catchlog (>=1.2.2); extra == 'test'
Requires-Dist: flaky (>=3.3.0); extra == 'test'
Requires-Dist: nose (>=1.3.7); extra == 'test'
Requires-Dist: mne (~=0.17.0); extra == 'test'
Requires-Dist: scipy; extra == 'test'
Requires-Dist: matplotlib; extra == 'test'
